{"stat.useItem.381":10,"stat.useItem.46":11,"achievement.openInventory":66,"stat.damageDealt":625,"stat.useItem.23":1,"stat.useItem.3":25,"achievement.exploreAllBiomes":{"value":0,"progress":["Forest","Extreme Hills+","Extreme Hills","Plains","Birch Forest","Roofed Forest","Swampland","River","Birch Forest Hills","ForestHills"]},"stat.useItem.259":245,"stat.killEntity.EntityHorse":1,"stat.useItem.69":5,"stat.climbOneCm":12,"stat.flyOneCm":377503,"stat.drop":7,"stat.killEntity.Chicken":1,"stat.useItem.120":13,"stat.useItem.29":6,"stat.killEntity.Creeper":4,"stat.diveOneCm":1653,"stat.useItem.158":4,"stat.useItem.383":33,"stat.useItem.131":2,"stat.useItem.287":15,"achievement.mineWood":1,"stat.playOneMinute":113012,"stat.killEntity.Spider":1,"stat.useItem.329":14,"stat.jump":103,"stat.swimOneCm":2218,"stat.useItem.331":12,"stat.mobKills":11,"stat.killEntity.Skeleton":1,"stat.killEntity.Squid":1,"stat.walkOneCm":45847,"stat.killEntity.Zombie":1,"stat.useItem.170":12}